neurocore_worker/__init__.py
neurocore_worker/main.py
neurocore_worker/transliter.py
neurocore_worker/tests/__init__.py
neurocore_worker/tests/test.py
qneuroworker-1.0.7.dist-info/METADATA
qneuroworker-1.0.7.dist-info/WHEEL
qneuroworker-1.0.7.dist-info/top_level.txt
qneuroworker-1.0.7.dist-info/RECORD
