Metadata-Version: 2.1
Name: qneuroworker
Version: 1.0.7
Author: PunchyArchy
Author-email: ksmdrmvscthny@gmail.com
Requires-Dist: transliterate
Requires-Dist: requests
Requires-Dist: pillow
